techflops_analyzer/__init__.py
techflops_analyzer/main.py
techflops_analyzer/prompts.py
techflops_analyzer-2025.12.20184937.dist-info/METADATA
techflops_analyzer-2025.12.20184937.dist-info/WHEEL
techflops_analyzer-2025.12.20184937.dist-info/top_level.txt
techflops_analyzer-2025.12.20184937.dist-info/RECORD
