Metadata-Version: 2.4
Name: techflops-analyzer
Version: 2025.12.20184937
Summary: A new package that processes text-based news headlines or article snippets (like the one provided) and returns a structured summary of the technology flop described, including key details such as the 
Author-email: techflops-analyzer <hi@eugene.plus>
License: MIT
Project-URL: Homepage, https://github.com/chigwell/techflops-analyzer
Requires-Python: >=3.9
Requires-Dist: langchain-llm7>=0.0.0
Requires-Dist: llmatch-messages>=0.0.0
Requires-Dist: langchain-core>=0.3.0
